pyramid_exclusive_request_methods/__init__.py
pyramid_exclusive_request_methods/tests/__init__.py
pyramid_exclusive_request_methods/tests/test_it.py
pyramid_exclusive_request_methods-0.0.7.dist-info/DESCRIPTION.rst
pyramid_exclusive_request_methods-0.0.7.dist-info/METADATA
pyramid_exclusive_request_methods-0.0.7.dist-info/RECORD
pyramid_exclusive_request_methods-0.0.7.dist-info/WHEEL
pyramid_exclusive_request_methods-0.0.7.dist-info/metadata.json
pyramid_exclusive_request_methods-0.0.7.dist-info/top_level.txt
