Metadata-Version: 2.0
Name: pyramid-exclusive-request-methods
Version: 0.0.7
Summary: UNKNOWN
Home-page: https://github.com/moriyoshi/pyramid_exclusive_request_methods
Author: Moriyoshi Koizumi
Author-email: mozo@mozo.jp
License: MIT
Keywords: pyramid request_method exclusive
Platform: UNKNOWN
Classifier: Development Status :: 4 - Beta
Classifier: Intended Audience :: Developers
Classifier: Programming Language :: Python
Classifier: Programming Language :: Python :: 2.7
Classifier: Programming Language :: Python :: 3
Classifier: Programming Language :: Python :: 3.4
Classifier: Programming Language :: Python :: 3.5
Classifier: Programming Language :: Python :: 3.6
Classifier: Programming Language :: Python :: Implementation :: CPython
Classifier: Programming Language :: Python :: Implementation :: PyPy
Classifier: Framework :: Pyramid
Requires-Dist: pyramid (>=1.7)
Requires-Dist: setuptools
Provides-Extra: doc
Requires-Dist: repoze.sphinx.autointerface; extra == 'doc'
Requires-Dist: sphinx; extra == 'doc'
